[
  {
    "organisation_name": "Orb Data Limited",
    "town_city": "London",
    "county": "",
    "type_rating": "Worker (A rating)",
    "route": "Skilled Worker"
  },
  {
    "organisation_name": "ORB Innovations Ltd",
    "town_city": "London",
    "county": "",
    "type_rating": "Worker (A rating)",
    "route": "Skilled Worker"
  },
  {
    "organisation_name": "ORB International Ltd",
    "town_city": "Holborn",
    "county": "London",
    "type_rating": "Worker (A rating)",
    "route": "Skilled Worker"
  },
  {
    "organisation_name": "Orbach &amp; Chambers Ltd",
    "town_city": "London",
    "county": "",
    "type_rating": "Worker (A rating)",
    "route": "Skilled Worker"
  },
  {
    "organisation_name": "Orben Limited",
    "town_city": "Greater Manchester",
    "county": "",
    "type_rating": "Worker (A rating)",
    "route": "Skilled Worker"
  },
  {
    "organisation_name": "Orbian Management Limited",
    "town_city": "London",
    "county": "",
    "type_rating": "Worker (A rating)",
    "route": "Skilled Worker"
  },
  {
    "organisation_name": "Orbis Advisory Limited",
    "town_city": "London",
    "county": "",
    "type_rating": "Worker (A rating)",
    "route": "Skilled Worker"
  },
  {
    "organisation_name": "Orbis Care Limited",
    "town_city": "Henley in Arden",
    "county": "Warwickshire",
    "type_rating": "Worker (A rating)",
    "route": "Skilled Worker"
  },
  {
    "organisation_name": "Orbis Consultants Limited",
    "town_city": "London",
    "county": "",
    "type_rating": "Worker (A rating)",
    "route": "Skilled Worker"
  },
  {
    "organisation_name": "Orbis Consultants Limited",
    "town_city": "London",
    "county": "",
    "type_rating": "Worker (A rating)",
    "route": "Global Business Mobility: Senior or Specialist Worker"
  },
  {
    "organisation_name": "Orbis Education and Care",
    "town_city": "Cardiff",
    "county": "",
    "type_rating": "Worker (A rating)",
    "route": "Skilled Worker"
  },
  {
    "organisation_name": "Orbis Investment Advisory Limited",
    "town_city": "London",
    "county": "",
    "type_rating": "Worker (A rating)",
    "route": "Skilled Worker"
  },
  {
    "organisation_name": "Orbis Investment Advisory Limited",
    "town_city": "London",
    "county": "",
    "type_rating": "Worker (A rating)",
    "route": "Global Business Mobility: Senior or Specialist Worker"
  },
  {
    "organisation_name": "Orbis Investments (U.K.) Limited",
    "town_city": "London",
    "county": "",
    "type_rating": "Worker (A rating)",
    "route": "Skilled Worker"
  },
  {
    "organisation_name": "Orbis Investments (U.K.) Limited",
    "town_city": "London",
    "county": "",
    "type_rating": "Worker (A rating)",
    "route": "Global Business Mobility: Senior or Specialist Worker"
  },
  {
    "organisation_name": "Orbis Partners Limited",
    "town_city": "Birmingham",
    "county": "",
    "type_rating": "Worker (A rating)",
    "route": "Skilled Worker"
  },
  {
    "organisation_name": "Orbis Portfolio Management (Europe) LLP",
    "town_city": "London",
    "county": "",
    "type_rating": "Worker (A rating)",
    "route": "Skilled Worker"
  },
  {
    "organisation_name": "Orbis Portfolio Management (Europe) LLP",
    "town_city": "London",
    "county": "",
    "type_rating": "Worker (A rating)",
    "route": "Global Business Mobility: Senior or Specialist Worker"
  },
  {
    "organisation_name": "Orbis Support Ltd",
    "town_city": "North Shields",
    "county": "Tyne and Wear",
    "type_rating": "Worker (A rating)",
    "route": "Skilled Worker"
  },
  {
    "organisation_name": "Orbit Cargo Services Ltd",
    "town_city": "COLNBROOK",
    "county": "",
    "type_rating": "Worker (A rating)",
    "route": "Skilled Worker"
  },
  {
    "organisation_name": "Orbit Discovery Ltd",
    "town_city": "Oxford",
    "county": "",
    "type_rating": "Worker (A rating)",
    "route": "Skilled Worker"
  },
  {
    "organisation_name": "Orbit Energy Limited",
    "town_city": "London",
    "county": "",
    "type_rating": "Worker (A rating)",
    "route": "Skilled Worker"
  },
  {
    "organisation_name": "Orbit Fab Ltd",
    "town_city": "Didcot",
    "county": "Oxfordshire",
    "type_rating": "Worker (A rating)",
    "route": "Global Business Mobility: Senior or Specialist Worker"
  },
  {
    "organisation_name": "Orbit Fab Ltd",
    "town_city": "Didcot",
    "county": "Oxfordshire",
    "type_rating": "Worker (A rating)",
    "route": "Skilled Worker"
  },
  {
    "organisation_name": "ORBIT FOOD AND BEVERAGE LTD",
    "town_city": "Croydon",
    "county": "",
    "type_rating": "Worker (A rating)",
    "route": "Skilled Worker"
  },
  {
    "organisation_name": "Orbit Grill Limited",
    "town_city": "Acton",
    "county": "London",
    "type_rating": "Worker (A rating)",
    "route": "Skilled Worker"
  },
  {
    "organisation_name": "Orbit iTech Ltd",
    "town_city": "Birmingham",
    "county": "West Midlands",
    "type_rating": "Worker (A rating)",
    "route": "Skilled Worker"
  },
  {
    "organisation_name": "Orbit Media Solutions Limited",
    "town_city": "London",
    "county": "",
    "type_rating": "Worker (A rating)",
    "route": "Skilled Worker"
  },
  {
    "organisation_name": "Orbit Metro Limited",
    "town_city": "London",
    "county": "",
    "type_rating": "Worker (A rating)",
    "route": "Skilled Worker"
  },
  {
    "organisation_name": "Orbit Partners Limited",
    "town_city": "London",
    "county": "",
    "type_rating": "Worker (A rating)",
    "route": "Global Business Mobility: Senior or Specialist Worker"
  },
  {
    "organisation_name": "Orbit Partners Limited",
    "town_city": "London",
    "county": "",
    "type_rating": "Worker (A rating)",
    "route": "Skilled Worker"
  },
  {
    "organisation_name": "Orbital Astronautics Ltd",
    "town_city": "Goring",
    "county": "Oxfordshire",
    "type_rating": "Worker (A rating)",
    "route": "Skilled Worker"
  },
  {
    "organisation_name": "ORBITAL CARE SERVICES 2 LTD",
    "town_city": "Kenley",
    "county": "",
    "type_rating": "Worker (A rating)",
    "route": "Skilled Worker"
  },
  {
    "organisation_name": "Orbital Civil Engineering Ltd",
    "town_city": "Essex",
    "county": "",
    "type_rating": "Worker (A rating)",
    "route": "Skilled Worker"
  },
  {
    "organisation_name": "Orbital Education Limited",
    "town_city": "Cheadle Hulme",
    "county": "Cheshire",
    "type_rating": "Worker (A rating)",
    "route": "Skilled Worker"
  },
  {
    "organisation_name": "Orbital Express Launch Limited",
    "town_city": "Forres",
    "county": "Moray",
    "type_rating": "Worker (A rating)",
    "route": "Skilled Worker"
  },
  {
    "organisation_name": "Orbital Express Launch Limited",
    "town_city": "Forres",
    "county": "Moray",
    "type_rating": "Worker (A rating)",
    "route": "Global Business Mobility: Senior or Specialist Worker"
  },
  {
    "organisation_name": "Orbital Gas Systems Limited",
    "town_city": "Stone",
    "county": "Staffordshire",
    "type_rating": "Worker (A rating)",
    "route": "Skilled Worker"
  },
  {
    "organisation_name": "Orbital Gas Systems Limited",
    "town_city": "Stone",
    "county": "Staffordshire",
    "type_rating": "Worker (A rating)",
    "route": "Global Business Mobility: Senior or Specialist Worker"
  },
  {
    "organisation_name": "Orbital Materials Ltd",
    "town_city": "Elsted",
    "county": "Surrey",
    "type_rating": "Worker (A rating)",
    "route": "Global Business Mobility: Senior or Specialist Worker"
  },
  {
    "organisation_name": "Orbital Materials Ltd",
    "town_city": "Elsted",
    "county": "Surrey",
    "type_rating": "Worker (A rating)",
    "route": "Skilled Worker"
  },
  {
    "organisation_name": "Orbital Witness Limited",
    "town_city": "London",
    "county": "",
    "type_rating": "Worker (A rating)",
    "route": "Skilled Worker"
  },
  {
    "organisation_name": "Orbitvu Sales Ltd",
    "town_city": "Northfield Daventry",
    "county": "",
    "type_rating": "Worker (A rating)",
    "route": "Skilled Worker"
  },
  {
    "organisation_name": "Orbix UK limited",
    "town_city": "Walton-On-Thames",
    "county": "Surrey",
    "type_rating": "Worker (A rating)",
    "route": "Skilled Worker"
  },
  {
    "organisation_name": "ORCA Computing LTD",
    "town_city": "London",
    "county": "London",
    "type_rating": "Worker (A rating)",
    "route": "Skilled Worker"
  },
  {
    "organisation_name": "Orca CT Trading Ltd",
    "town_city": "Corby",
    "county": "",
    "type_rating": "Worker (A rating)",
    "route": "Skilled Worker"
  },
  {
    "organisation_name": "Orca Scan Limited",
    "town_city": "Cambridge",
    "county": "",
    "type_rating": "Worker (A rating)",
    "route": "Skilled Worker"
  },
  {
    "organisation_name": "Orca Security UK Ltd",
    "town_city": "Cambridge",
    "county": "",
    "type_rating": "Worker (A rating)",
    "route": "Skilled Worker"
  },
  {
    "organisation_name": "Orcades Marine Management Consultants Ltd.",
    "town_city": "Kirkwall",
    "county": "Orkney",
    "type_rating": "Worker (A rating)",
    "route": "Skilled Worker"
  },
  {
    "organisation_name": "Orcan Intelligence Ltd",
    "town_city": "London",
    "county": "",
    "type_rating": "Worker (A rating)",
    "route": "Skilled Worker"
  },
  {
    "organisation_name": "Orchard Care (South West) Ltd",
    "town_city": "Looe",
    "county": "",
    "type_rating": "Worker (A rating)",
    "route": "Skilled Worker"
  },
  {
    "organisation_name": "Orchard Care Group Limited",
    "town_city": "Wrexham",
    "county": "Wrexham",
    "type_rating": "Worker (A rating)",
    "route": "Skilled Worker"
  },
  {
    "organisation_name": "ORCHARD CARE GROUP LIMITED",
    "town_city": "Wrexham",
    "county": "",
    "type_rating": "Worker (A rating)",
    "route": "Skilled Worker"
  },
  {
    "organisation_name": "ORCHARD CARE HOMES",
    "town_city": "Harrogate",
    "county": "North Yorkshire",
    "type_rating": "Worker (A rating)",
    "route": "Skilled Worker"
  },
  {
    "organisation_name": "Orchard Corner Ltd",
    "town_city": "Leamington Spa",
    "county": "Warwickshire",
    "type_rating": "Worker (A rating)",
    "route": "Skilled Worker"
  },
  {
    "organisation_name": "Orchard Global Asset Management LLP",
    "town_city": "London",
    "county": "",
    "type_rating": "Worker (A rating)",
    "route": "Skilled Worker"
  },
  {
    "organisation_name": "Orchard Global Asset Management LLP",
    "town_city": "London",
    "county": "",
    "type_rating": "Worker (A rating)",
    "route": "Global Business Mobility: Senior or Specialist Worker"
  },
  {
    "organisation_name": "Orchard Hill College Academy Trust",
    "town_city": "Sutton",
    "county": "Surrey",
    "type_rating": "Worker (A rating)",
    "route": "Skilled Worker"
  },
  {
    "organisation_name": "Orchard Homes Limited",
    "town_city": "Nottingham",
    "county": "",
    "type_rating": "Worker (A rating)",
    "route": "Skilled Worker"
  },
  {
    "organisation_name": "Orchard house (midlands) limited",
    "town_city": "sutton coldfield",
    "county": "west midlands",
    "type_rating": "Worker (A rating)",
    "route": "Skilled Worker"
  },
  {
    "organisation_name": "Orchard House Nursing Home Limited",
    "town_city": "Mablethorpe",
    "county": "Lincolnshire",
    "type_rating": "Worker (A rating)",
    "route": "Skilled Worker"
  },
  {
    "organisation_name": "ORCHARD HOUSE NURSING HOME LTD",
    "town_city": "MABLETHORPE",
    "county": "",
    "type_rating": "Worker (A rating)",
    "route": "Skilled Worker"
  },
  {
    "organisation_name": "Orchard House, Bath Ltd",
    "town_city": "Bath",
    "county": "Somerset",
    "type_rating": "Worker (A rating)",
    "route": "Skilled Worker"
  },
  {
    "organisation_name": "Orchard Lea Nursing Home",
    "town_city": "Cullompton",
    "county": "Devon",
    "type_rating": "Worker (A rating)",
    "route": "Skilled Worker"
  },
  {
    "organisation_name": "Orchard Manor View Limited",
    "town_city": "Leicester",
    "county": "",
    "type_rating": "Worker (A rating)",
    "route": "Skilled Worker"
  },
  {
    "organisation_name": "Orchard Media and Events Ltd",
    "town_city": "Cardiff",
    "county": "",
    "type_rating": "Temporary Worker (A rating)",
    "route": "Creative Worker"
  },
  {
    "organisation_name": "Orchard Media and Events Ltd",
    "town_city": "Cardiff",
    "county": "",
    "type_rating": "Worker (A rating)",
    "route": "Skilled Worker"
  },
  {
    "organisation_name": "Orchard Medical Practice",
    "town_city": "Mansfield",
    "county": "Nottinghamshire",
    "type_rating": "Worker (A rating)",
    "route": "Skilled Worker"
  },
  {
    "organisation_name": "Orchard Mushrooms Ltd",
    "town_city": "Loughgall",
    "county": "Co Armagh",
    "type_rating": "Worker (A rating)",
    "route": "Skilled Worker"
  },
  {
    "organisation_name": "Orchard Orthodontics",
    "town_city": "London",
    "county": "",
    "type_rating": "Worker (A rating)",
    "route": "Skilled Worker"
  },
  {
    "organisation_name": "Orchard Park Homes (BP) Ltd.",
    "town_city": "Eastbourne",
    "county": "",
    "type_rating": "Worker (A rating)",
    "route": "Skilled Worker"
  },
  {
    "organisation_name": "Orchard Restaurant Ltd",
    "town_city": "Blackpool",
    "county": "",
    "type_rating": "Worker (A rating)",
    "route": "Skilled Worker"
  },
  {
    "organisation_name": "ORCHARD ROAD DENTAL PRACTICE LTD",
    "town_city": "FORESS",
    "county": "",
    "type_rating": "Worker (A rating)",
    "route": "Skilled Worker"
  },
  {
    "organisation_name": "Orchard Surgery and Partners",
    "town_city": "Dereham",
    "county": "Norfolk",
    "type_rating": "Worker (A rating)",
    "route": "Skilled Worker"
  },
  {
    "organisation_name": "Orchard Surgery",
    "town_city": "Stoke on Trent",
    "county": "",
    "type_rating": "Worker (A rating)",
    "route": "Skilled Worker"
  },
  {
    "organisation_name": "Orchard Veterinary Centre Ltd",
    "town_city": "Oldbury",
    "county": "",
    "type_rating": "Worker (A rating)",
    "route": "Skilled Worker"
  },
  {
    "organisation_name": "Orchard View Care Services LTD",
    "town_city": "Crediton",
    "county": "Devon",
    "type_rating": "Worker (A rating)",
    "route": "Skilled Worker"
  },
  {
    "organisation_name": "ORCHARDS PHARMACY",
    "town_city": "WEST DRAYTON",
    "county": "",
    "type_rating": "Worker (A rating)",
    "route": "Skilled Worker"
  },
  {
    "organisation_name": "Orchestra of the Age of Enlightenment",
    "town_city": "London",
    "county": "",
    "type_rating": "Temporary Worker (A rating)",
    "route": "Creative Worker"
  },
  {
    "organisation_name": "ORCHESTRATING IDENTITY LIMITED",
    "town_city": "CROYDON",
    "county": "SURREY",
    "type_rating": "Worker (A rating)",
    "route": "Skilled Worker"
  },
  {
    "organisation_name": "Orchid Am Limited",
    "town_city": "Manchester",
    "county": "",
    "type_rating": "Temporary Worker (A rating)",
    "route": "Creative Worker"
  },
  {
    "organisation_name": "Orchid Beauty Salon ltd",
    "town_city": "London",
    "county": "",
    "type_rating": "Worker (A rating)",
    "route": "Skilled Worker"
  },
  {
    "organisation_name": "Orchid Care Homes Limited t/a Springfield Care Home",
    "town_city": "March",
    "county": "",
    "type_rating": "Worker (A rating)",
    "route": "Skilled Worker"
  },
  {
    "organisation_name": "Orchid Dental Practice",
    "town_city": "London",
    "county": "",
    "type_rating": "Worker (A rating)",
    "route": "Skilled Worker"
  },
  {
    "organisation_name": "Orchid Global Sourcing Ltd",
    "town_city": "London",
    "county": "",
    "type_rating": "Worker (A rating)",
    "route": "Skilled Worker"
  },
  {
    "organisation_name": "Orchid Home Care Support Limited",
    "town_city": "Bolton",
    "county": "",
    "type_rating": "Worker (A rating)",
    "route": "Skilled Worker"
  },
  {
    "organisation_name": "Orchid House Surgery",
    "town_city": "Ferndown",
    "county": "Dorset",
    "type_rating": "Worker (A rating)",
    "route": "Skilled Worker"
  },
  {
    "organisation_name": "ORCHID MANAGEMENT LIMITED T/A COSMO BRISTOL",
    "town_city": "BRISTOL",
    "county": "",
    "type_rating": "Worker (A rating)",
    "route": "Skilled Worker"
  },
  {
    "organisation_name": "Orchid Money Transfer Ltd",
    "town_city": "London",
    "county": "",
    "type_rating": "Worker (A rating)",
    "route": "Skilled Worker"
  },
  {
    "organisation_name": "Orchid Private Company Limited",
    "town_city": " London,",
    "county": "",
    "type_rating": "Worker (A rating)",
    "route": "Skilled Worker"
  },
  {
    "organisation_name": "Orchid Supported Living Limited",
    "town_city": "Birmingham",
    "county": "West Midlands",
    "type_rating": "Worker (A rating)",
    "route": "Skilled Worker"
  },
  {
    "organisation_name": "Orchid Wellness Limited",
    "town_city": "Fleet",
    "county": "Hampshire",
    "type_rating": "Worker (A rating)",
    "route": "Skilled Worker"
  },
  {
    "organisation_name": "Orchid Woodlands Healthcare Ltd",
    "town_city": "Manchester",
    "county": "",
    "type_rating": "Worker (A rating)",
    "route": "Skilled Worker"
  },
  {
    "organisation_name": "Orchids Care Ltd",
    "town_city": "Doncaster",
    "county": "South Yorkshire",
    "type_rating": "Worker (A rating)",
    "route": "Skilled Worker"
  },
  {
    "organisation_name": "Orchis Living Ltd",
    "town_city": "Farnborough",
    "county": "Hampshire",
    "type_rating": "Worker (A rating)",
    "route": "Skilled Worker"
  },
  {
    "organisation_name": "Orci Trials Limited",
    "town_city": "Solihull",
    "county": "",
    "type_rating": "Worker (A rating)",
    "route": "Skilled Worker"
  },
  {
    "organisation_name": "Orcom Civvals Limited",
    "town_city": "London",
    "county": "",
    "type_rating": "Worker (A rating)",
    "route": "Skilled Worker"
  },
  {
    "organisation_name": "Orcone Care Ltd",
    "town_city": "Birmingham",
    "county": "",
    "type_rating": "Worker (A rating)",
    "route": "Skilled Worker"
  },
  {
    "organisation_name": "Ordara Limited",
    "town_city": "Andover",
    "county": "",
    "type_rating": "Worker (A rating)",
    "route": "Skilled Worker"
  },
  {
    "organisation_name": "ORDEN Ltd",
    "town_city": "London",
    "county": "London",
    "type_rating": "Temporary Worker (A rating)",
    "route": "Creative Worker"
  }
]