[
  {
    "organisation_name": "Right at Home Bristol East",
    "town_city": "Bristol",
    "county": "",
    "type_rating": "Worker (A rating)",
    "route": "Skilled Worker"
  },
  {
    "organisation_name": "Right at Home Mid Cheshire",
    "town_city": "Northwich",
    "county": "Cheshire",
    "type_rating": "Worker (A rating)",
    "route": "Skilled Worker"
  },
  {
    "organisation_name": "Right at Home South Cheshire",
    "town_city": "Nantwich",
    "county": "Cheshire",
    "type_rating": "Worker (A rating)",
    "route": "Skilled Worker"
  },
  {
    "organisation_name": "Right at Home Stockport &amp; Didsbury",
    "town_city": "Stockport",
    "county": "Greater Manchester",
    "type_rating": "Worker (A rating)",
    "route": "Skilled Worker"
  },
  {
    "organisation_name": "Right at Home Telford t/a Wadlow Care Limited",
    "town_city": "Telford",
    "county": "Shropshire",
    "type_rating": "Worker (A rating)",
    "route": "Skilled Worker"
  },
  {
    "organisation_name": "Right At Home Worthing &amp; Shoreham",
    "town_city": "Shoreham-by-Sea",
    "county": "West Sussex",
    "type_rating": "Worker (A rating)",
    "route": "Skilled Worker"
  },
  {
    "organisation_name": "Right Building Construction Limited",
    "town_city": "Slough",
    "county": "",
    "type_rating": "Worker (A rating)",
    "route": "Skilled Worker"
  },
  {
    "organisation_name": "RIGHT CARE (NW) LTD",
    "town_city": "BOLTON",
    "county": "",
    "type_rating": "Worker (A rating)",
    "route": "Skilled Worker"
  },
  {
    "organisation_name": "Right Care 4 U",
    "town_city": "South Harrow",
    "county": "Middlesex",
    "type_rating": "Worker (A rating)",
    "route": "Skilled Worker"
  },
  {
    "organisation_name": "Right Care Services Ltd",
    "town_city": "Derby",
    "county": "",
    "type_rating": "Worker (A rating)",
    "route": "Skilled Worker"
  },
  {
    "organisation_name": "Right Carpet and Flooring Ltd",
    "town_city": "Dunstable",
    "county": "",
    "type_rating": "Worker (A rating)",
    "route": "Skilled Worker"
  },
  {
    "organisation_name": "Right Choice Care Ltd",
    "town_city": "Kent",
    "county": "",
    "type_rating": "Worker (A rating)",
    "route": "Skilled Worker"
  },
  {
    "organisation_name": "RIGHT CHOICE DOUBLE GLAZING LTD",
    "town_city": "Romford",
    "county": "",
    "type_rating": "Worker (A rating)",
    "route": "Skilled Worker"
  },
  {
    "organisation_name": "RIGHT CHOICE ESTATES LTD",
    "town_city": "London",
    "county": "",
    "type_rating": "Worker (A rating)",
    "route": "Skilled Worker"
  },
  {
    "organisation_name": "Right Choice Glazing Limited",
    "town_city": "Ilford",
    "county": "",
    "type_rating": "Worker (A rating)",
    "route": "Skilled Worker"
  },
  {
    "organisation_name": "Right Choice Homerton Ltd T/a EXPA Local Supermarket",
    "town_city": "London",
    "county": "",
    "type_rating": "Worker (A rating)",
    "route": "Skilled Worker"
  },
  {
    "organisation_name": "Right Choice Insurance Brokers Ltd",
    "town_city": "Romford",
    "county": "Essex",
    "type_rating": "Worker (A rating)",
    "route": "Skilled Worker"
  },
  {
    "organisation_name": "Right Choice logistics Limited",
    "town_city": "London",
    "county": "",
    "type_rating": "Worker (A rating)",
    "route": "Skilled Worker"
  },
  {
    "organisation_name": "Right Choice Medicare Limited",
    "town_city": "Highland",
    "county": "",
    "type_rating": "Worker (A rating)",
    "route": "Skilled Worker"
  },
  {
    "organisation_name": "Right Choice Recruitment Solutions",
    "town_city": "Camberley",
    "county": "Surrey",
    "type_rating": "Worker (A rating)",
    "route": "Skilled Worker"
  },
  {
    "organisation_name": "Right Choice Service Ltd",
    "town_city": "London",
    "county": "Middlesex",
    "type_rating": "Worker (A rating)",
    "route": "Skilled Worker"
  },
  {
    "organisation_name": "Right Choices",
    "town_city": "Wigan",
    "county": "",
    "type_rating": "Worker (A rating)",
    "route": "Skilled Worker"
  },
  {
    "organisation_name": "Right Cue Consulting Services Limited",
    "town_city": "Basingstoke",
    "county": "",
    "type_rating": "Worker (A rating)",
    "route": "Skilled Worker"
  },
  {
    "organisation_name": "Right Food Ltd",
    "town_city": "Leigh",
    "county": "",
    "type_rating": "Worker (A rating)",
    "route": "Skilled Worker"
  },
  {
    "organisation_name": "Right Formula Ltd",
    "town_city": "London",
    "county": "",
    "type_rating": "Worker (A rating)",
    "route": "Skilled Worker"
  },
  {
    "organisation_name": "Right Hand Group LTD",
    "town_city": "London",
    "county": "",
    "type_rating": "Worker (A rating)",
    "route": "Skilled Worker"
  },
  {
    "organisation_name": "Right Holidays Ltd",
    "town_city": "London",
    "county": "",
    "type_rating": "Worker (A rating)",
    "route": "Skilled Worker"
  },
  {
    "organisation_name": "Right Home Estates Limited",
    "town_city": "Wembley",
    "county": "Middx",
    "type_rating": "Worker (A rating)",
    "route": "Skilled Worker"
  },
  {
    "organisation_name": "Right Hook Studio Ltd",
    "town_city": "Spennymoor",
    "county": "Durham",
    "type_rating": "Worker (A rating)",
    "route": "Skilled Worker"
  },
  {
    "organisation_name": "Right Kare Ltd T/A Right at Home Maidenhead",
    "town_city": "Maidenhead",
    "county": "",
    "type_rating": "Worker (A rating)",
    "route": "Skilled Worker"
  },
  {
    "organisation_name": "Right Law Solicitors Ltd",
    "town_city": "London",
    "county": "London",
    "type_rating": "Worker (A rating)",
    "route": "Skilled Worker"
  },
  {
    "organisation_name": "Right Medicare Limited",
    "town_city": "Dunstable",
    "county": "",
    "type_rating": "Worker (A rating)",
    "route": "Skilled Worker"
  },
  {
    "organisation_name": "RIGHT NOW CONTRACTING LTD",
    "town_city": "Bradford",
    "county": "",
    "type_rating": "Worker (A rating)",
    "route": "Skilled Worker"
  },
  {
    "organisation_name": "RIGHT PRICE (MCR) LIMITED",
    "town_city": "Manchester",
    "county": "",
    "type_rating": "Worker (A rating)",
    "route": "Skilled Worker"
  },
  {
    "organisation_name": "RIGHT PRICE (WHOLESALE) LTD",
    "town_city": "HAYES",
    "county": "",
    "type_rating": "Worker (A rating)",
    "route": "Skilled Worker"
  },
  {
    "organisation_name": "RIGHT STAFF RECRUITMENT LIMITED",
    "town_city": "Cannock",
    "county": "",
    "type_rating": "Worker (A rating)",
    "route": "Skilled Worker"
  },
  {
    "organisation_name": "RIGHT SUPPORT MANAGEMENT LIMITED",
    "town_city": "LONDON",
    "county": "",
    "type_rating": "Worker (A rating)",
    "route": "Skilled Worker"
  },
  {
    "organisation_name": "Right Temp Control Ltd",
    "town_city": "Croydon",
    "county": "",
    "type_rating": "Worker (A rating)",
    "route": "Skilled Worker"
  },
  {
    "organisation_name": "Right There",
    "town_city": "Glasgow",
    "county": "Scotland",
    "type_rating": "Worker (A rating)",
    "route": "Skilled Worker"
  },
  {
    "organisation_name": "Right Time Estates Ltd",
    "town_city": "Southall",
    "county": "",
    "type_rating": "Worker (A rating)",
    "route": "Skilled Worker"
  },
  {
    "organisation_name": "Right Time Recruitment",
    "town_city": "Oldbury",
    "county": "Oldbury",
    "type_rating": "Worker (A rating)",
    "route": "Skilled Worker"
  },
  {
    "organisation_name": "Right Time Right Place Limited T/A Caffee Oro",
    "town_city": "Merseyside",
    "county": "",
    "type_rating": "Worker (A rating)",
    "route": "Skilled Worker"
  },
  {
    "organisation_name": "RIGHT TO CARE LTD",
    "town_city": "DUDLEY",
    "county": "WEST MIDLANDS",
    "type_rating": "Worker (A rating)",
    "route": "Skilled Worker"
  },
  {
    "organisation_name": "Right to Life UK",
    "town_city": "London",
    "county": "",
    "type_rating": "Worker (A rating)",
    "route": "Skilled Worker"
  },
  {
    "organisation_name": "Right To Play International",
    "town_city": "London",
    "county": "",
    "type_rating": "Worker (A rating)",
    "route": "Skilled Worker"
  },
  {
    "organisation_name": "Right To Play International",
    "town_city": "London",
    "county": "",
    "type_rating": "Worker (A rating)",
    "route": "Global Business Mobility: Senior or Specialist Worker"
  },
  {
    "organisation_name": "Right Utility LTD",
    "town_city": "Newport",
    "county": "Wales",
    "type_rating": "Worker (A rating)",
    "route": "Skilled Worker"
  },
  {
    "organisation_name": "Rightbuild Building Solutions Ltd",
    "town_city": "Romford",
    "county": "",
    "type_rating": "Worker (A rating)",
    "route": "Skilled Worker"
  },
  {
    "organisation_name": "Rightcard Payment Services Limited t/a Lemonade Finance",
    "town_city": "Kent",
    "county": "",
    "type_rating": "Worker (A rating)",
    "route": "Skilled Worker"
  },
  {
    "organisation_name": "Rightdose Healthcare Limited",
    "town_city": "Glasgow",
    "county": "Scotland",
    "type_rating": "Worker (A rating)",
    "route": "Skilled Worker"
  },
  {
    "organisation_name": "RIGHTEOUS BRANCH LIMITED",
    "town_city": "Coalville",
    "county": "",
    "type_rating": "Worker (A rating)",
    "route": "Skilled Worker"
  },
  {
    "organisation_name": "Rightindem Limited",
    "town_city": "London",
    "county": "",
    "type_rating": "Worker (A rating)",
    "route": "Skilled Worker"
  },
  {
    "organisation_name": "Rightmove Group Ltd",
    "town_city": "Milton Keynes",
    "county": "",
    "type_rating": "Worker (A rating)",
    "route": "Skilled Worker"
  },
  {
    "organisation_name": "RIGHTNOW LTD",
    "town_city": "Reading",
    "county": "Birkshire",
    "type_rating": "Worker (A rating)",
    "route": "Skilled Worker"
  },
  {
    "organisation_name": "RIGHTPAK LTD",
    "town_city": "KINGS LANGLEY",
    "county": "",
    "type_rating": "Worker (A rating)",
    "route": "Skilled Worker"
  },
  {
    "organisation_name": "RIGHTPHARM LTD",
    "town_city": "HARROW",
    "county": "",
    "type_rating": "Worker (A rating)",
    "route": "Skilled Worker"
  },
  {
    "organisation_name": "Rightroad Edtech Limited",
    "town_city": "Sutton",
    "county": "",
    "type_rating": "Worker (A rating)",
    "route": "Skilled Worker"
  },
  {
    "organisation_name": "RightShip UK Ltd",
    "town_city": "London",
    "county": "",
    "type_rating": "Worker (A rating)",
    "route": "Skilled Worker"
  },
  {
    "organisation_name": "RightShip UK Ltd",
    "town_city": "London",
    "county": "",
    "type_rating": "Worker (A rating)",
    "route": "Global Business Mobility: Senior or Specialist Worker"
  },
  {
    "organisation_name": "Rightsline Software UK Ltd",
    "town_city": "London",
    "county": "",
    "type_rating": "Worker (A rating)",
    "route": "Skilled Worker"
  },
  {
    "organisation_name": "Rightsline Software UK Ltd",
    "town_city": "London",
    "county": "",
    "type_rating": "Worker (A rating)",
    "route": "Global Business Mobility: Senior or Specialist Worker"
  },
  {
    "organisation_name": "RIGHTWAY TRADERS N/W LIMITED",
    "town_city": "Manchester",
    "county": "",
    "type_rating": "Worker (A rating)",
    "route": "Skilled Worker"
  },
  {
    "organisation_name": "RIGHTWAY WHOLESALE LIMITED",
    "town_city": "Glasgow",
    "county": "",
    "type_rating": "Worker (A rating)",
    "route": "Skilled Worker"
  },
  {
    "organisation_name": "Rigibore Ltd",
    "town_city": "Hayle",
    "county": "Cornwall",
    "type_rating": "Worker (A rating)",
    "route": "Skilled Worker"
  },
  {
    "organisation_name": "Rigid healthcare group limited",
    "town_city": "Coventry",
    "county": "West Midlands",
    "type_rating": "Worker (A rating)",
    "route": "Skilled Worker"
  },
  {
    "organisation_name": "Rigmar Services Ltd",
    "town_city": "Aberdeen",
    "county": "Aberdeenshire",
    "type_rating": "Worker (A rating)",
    "route": "Skilled Worker"
  },
  {
    "organisation_name": "RigNet UK Limited",
    "town_city": "Westhill",
    "county": "Aberdeenshire",
    "type_rating": "Worker (A rating)",
    "route": "Skilled Worker"
  },
  {
    "organisation_name": "RigNet UK Limited",
    "town_city": "Westhill",
    "county": "Aberdeenshire",
    "type_rating": "Worker (A rating)",
    "route": "Global Business Mobility: Senior or Specialist Worker"
  },
  {
    "organisation_name": "RigQuip Drilling Services Ltd",
    "town_city": "Aberdeen",
    "county": "Aberdeen City",
    "type_rating": "Worker (A rating)",
    "route": "Skilled Worker"
  },
  {
    "organisation_name": "Rihana Ltd",
    "town_city": "Gillingham",
    "county": "Kent",
    "type_rating": "Worker (A rating)",
    "route": "Skilled Worker"
  },
  {
    "organisation_name": "RIIFO UK LTD",
    "town_city": "Burntwood",
    "county": "Staffordshire",
    "type_rating": "Worker (A rating)",
    "route": "Skilled Worker"
  },
  {
    "organisation_name": "RIJAH LIMITED T/A MEGA MART",
    "town_city": "Ilford",
    "county": "Essex",
    "type_rating": "Worker (A rating)",
    "route": "Skilled Worker"
  },
  {
    "organisation_name": "RIJYOS TECHNOVATIONS LTD",
    "town_city": "Solihull",
    "county": "West Midlands",
    "type_rating": "Worker (A rating)",
    "route": "Skilled Worker"
  },
  {
    "organisation_name": "RIKA GLOBAL LTD",
    "town_city": "Sutton Coldfield",
    "county": "Birmingham",
    "type_rating": "Worker (A rating)",
    "route": "Skilled Worker"
  },
  {
    "organisation_name": "Rika Group UK Ltd",
    "town_city": "London",
    "county": "",
    "type_rating": "Worker (A rating)",
    "route": "Skilled Worker"
  },
  {
    "organisation_name": "RIKKYO SCHOOL IN ENGLAND",
    "town_city": "HORSHAM",
    "county": "WEST SUSSEX",
    "type_rating": "Worker (A rating)",
    "route": "Skilled Worker"
  },
  {
    "organisation_name": "RIKKYO SCHOOL IN ENGLAND",
    "town_city": "HORSHAM",
    "county": "WEST SUSSEX",
    "type_rating": "Worker (A rating)",
    "route": "Tier 2 Ministers of Religion"
  },
  {
    "organisation_name": "Rik&#x27;s One Stop",
    "town_city": "Gillingham",
    "county": "",
    "type_rating": "Worker (A rating)",
    "route": "Skilled Worker"
  },
  {
    "organisation_name": "Riley &amp; Riley T/A The Queens Head",
    "town_city": "Farnham",
    "county": "Surrey",
    "type_rating": "Worker (A rating)",
    "route": "Skilled Worker"
  },
  {
    "organisation_name": "Riley Moss 2018 Limited",
    "town_city": "Preston",
    "county": "Lancashire",
    "type_rating": "Worker (A rating)",
    "route": "Skilled Worker"
  },
  {
    "organisation_name": "Riley Squares Limited T/As Nisa Local",
    "town_city": "Coventry",
    "county": "",
    "type_rating": "Worker (A rating)",
    "route": "Skilled Worker"
  },
  {
    "organisation_name": "RIMAC TECHNOLOGY R&amp;D UK LIMITED",
    "town_city": "Wellesbourne",
    "county": "",
    "type_rating": "Worker (A rating)",
    "route": "Skilled Worker"
  },
  {
    "organisation_name": "Rimadiamonds Ltd",
    "town_city": "London",
    "county": "",
    "type_rating": "Worker (A rating)",
    "route": "Skilled Worker"
  },
  {
    "organisation_name": "Rimaya Ltd",
    "town_city": "Romford",
    "county": "",
    "type_rating": "Worker (A rating)",
    "route": "Skilled Worker"
  },
  {
    "organisation_name": "Rimbal Ltd",
    "town_city": "London",
    "county": "",
    "type_rating": "Worker (A rating)",
    "route": "Skilled Worker"
  },
  {
    "organisation_name": "Rimell Racing",
    "town_city": "Leafield",
    "county": "Oxon",
    "type_rating": "Worker (A rating)",
    "route": "Skilled Worker"
  },
  {
    "organisation_name": "Rimes Technologies Limited",
    "town_city": "London",
    "county": "",
    "type_rating": "Worker (A rating)",
    "route": "Skilled Worker"
  },
  {
    "organisation_name": "Rimes Technologies Limited",
    "town_city": "London",
    "county": "",
    "type_rating": "Worker (A rating)",
    "route": "Global Business Mobility: Senior or Specialist Worker"
  },
  {
    "organisation_name": "Rimi Renovations Building Services Ltd",
    "town_city": "Romford",
    "county": "",
    "type_rating": "Worker (A rating)",
    "route": "Skilled Worker"
  },
  {
    "organisation_name": "RIMI SURGE LTD",
    "town_city": "CHESHAM",
    "county": "BUCKINGHAMSHIRE",
    "type_rating": "Worker (A rating)",
    "route": "Skilled Worker"
  },
  {
    "organisation_name": "Rimjhim Wimbourne Ltd",
    "town_city": "WIMBORNE",
    "county": "Dorset",
    "type_rating": "Worker (A rating)",
    "route": "Skilled Worker"
  },
  {
    "organisation_name": "Rimkus Consulting UK Limited",
    "town_city": "London",
    "county": "",
    "type_rating": "Worker (A rating)",
    "route": "Skilled Worker"
  },
  {
    "organisation_name": "RIMM SUSTAINABILITY LIMITED",
    "town_city": "London",
    "county": "",
    "type_rating": "Worker (A rating)",
    "route": "Skilled Worker"
  },
  {
    "organisation_name": "Rimmingtons Enterprises Limited",
    "town_city": "Bradford",
    "county": "West Yorkshire",
    "type_rating": "Worker (A rating)",
    "route": "Skilled Worker"
  },
  {
    "organisation_name": "RIMNEET DHILLON CONSTRUCTION LIMITED",
    "town_city": "NOTTINGHAM",
    "county": "",
    "type_rating": "Worker (A rating)",
    "route": "Skilled Worker"
  },
  {
    "organisation_name": "RIMO Capital Ltd",
    "town_city": "London",
    "county": "",
    "type_rating": "Worker (A rating)",
    "route": "Skilled Worker"
  },
  {
    "organisation_name": "Rimstock Limited",
    "town_city": "West Bromwich",
    "county": "",
    "type_rating": "Worker (A rating)",
    "route": "Skilled Worker"
  },
  {
    "organisation_name": "Rimtech Global Limited",
    "town_city": "Birmingham",
    "county": "West Midlands",
    "type_rating": "Worker (A rating)",
    "route": "Skilled Worker"
  },
  {
    "organisation_name": "RIMTEN UK LTD",
    "town_city": "Huddersfield,",
    "county": "",
    "type_rating": "Worker (A rating)",
    "route": "Skilled Worker"
  },
  {
    "organisation_name": "RIN SUSHI LTD",
    "town_city": "London",
    "county": "",
    "type_rating": "Worker (A rating)",
    "route": "Skilled Worker"
  }
]